squidward/__init__.py
squidward/gpc.py
squidward/gpr.py
squidward/utils.py
squidward/validation.py
squidward/kernels/__init__.py
squidward/kernels/distance.py
squidward/kernels/kernel_base.py
squidward/kernels/optimized_kernels.py
squidward-0.0.25.dist-info/LICENSE.md
squidward-0.0.25.dist-info/METADATA
squidward-0.0.25.dist-info/WHEEL
squidward-0.0.25.dist-info/top_level.txt
squidward-0.0.25.dist-info/RECORD
