Metadata-Version: 2.1
Name: squidward
Version: 0.0.25
Summary: Package for implementing Gaussian Process models in python.
Home-page: https://github.com/James-Montgomery/squidward
Author: James Montgomery
Author-email: jamesoneillmontgomery@gmail.com
License: UNKNOWN
Platform: UNKNOWN
Classifier: Programming Language :: Python :: 3
Classifier: License :: OSI Approved :: MIT License
Classifier: Operating System :: OS Independent
Requires-Dist: numpy (>=1.16.2)
Requires-Dist: scipy (>=1.1.0)
